colourlovers/__init__.py
colourlovers/clapi.py
colourlovers/data_containers.py
colourlovers-0.2.0.dist-info/LICENSE
colourlovers-0.2.0.dist-info/METADATA
colourlovers-0.2.0.dist-info/WHEEL
colourlovers-0.2.0.dist-info/top_level.txt
colourlovers-0.2.0.dist-info/RECORD
