Metadata-Version: 2.1
Name: colourlovers
Version: 0.2.0
Summary: A python wrapper for ColourLovers API
Home-page: https://github.com/juangallostra/Colourlovers-API-wrapper
Author: Juan Gallostra
Author-email: juangallostra@gmail.com
License: MIT
Download-URL: https://github.com/juangallostra/Colourlovers-API-wrapper/archive/0.2.0.tar.gz
Keywords: color,colour,palette,api,colourlovers,wrapper
Platform: UNKNOWN
Classifier: Development Status :: 3 - Alpha
Classifier: Intended Audience :: Developers
Classifier: License :: OSI Approved :: MIT License
Classifier: Programming Language :: Python :: 3
Requires-Dist: Pillow
